Topsis_Taruna_102003464/topsis.py
Topsis_Taruna_102003464-0.3.dist-info/METADATA
Topsis_Taruna_102003464-0.3.dist-info/WHEEL
Topsis_Taruna_102003464-0.3.dist-info/entry_points.txt
Topsis_Taruna_102003464-0.3.dist-info/license.txt
Topsis_Taruna_102003464-0.3.dist-info/top_level.txt
Topsis_Taruna_102003464-0.3.dist-info/RECORD
