Metadata-Version: 2.1
Name: Topsis-Taruna-102003464
Version: 0.3
Summary: This is package for topsis of version 0.3
Home-page: UNKNOWN
Author: Taruna Jain
Author-email: tjain_be20@thapar.edu
License: UNKNOWN
Platform: UNKNOWN
License-File: license.txt
Requires-Dist: pandas
